atnclib/__init__.py
atnclib/_modidx.py
atnclib/callbacks.py
atnclib/core.py
atnclib/data.py
atnclib/learner.py
atnclib/losses.py
atnclib/metrics.py
atnclib/model.py
atnclib/utility.py
atnclib/visualization.py
atnclib-0.0.10.dist-info/LICENSE
atnclib-0.0.10.dist-info/METADATA
atnclib-0.0.10.dist-info/WHEEL
atnclib-0.0.10.dist-info/entry_points.txt
atnclib-0.0.10.dist-info/top_level.txt
atnclib-0.0.10.dist-info/RECORD
